pyextrapolation/__init__.py
pyextrapolation/constant/__init__.py
pyextrapolation/constant/extrapolator.py
pyextrapolation-0.0.2.dist-info/LICENSE.md
pyextrapolation-0.0.2.dist-info/METADATA
pyextrapolation-0.0.2.dist-info/WHEEL
pyextrapolation-0.0.2.dist-info/top_level.txt
pyextrapolation-0.0.2.dist-info/RECORD
