Metadata-Version: 2.1
Name: pyextrapolation
Version: 0.0.2
Summary: A python package for multidimensional extrapolation via the solution of a partial differential equation
Home-page: https://github.com/murraycutforth/pyextrapolation
Author: Murray Cutforth
Author-email: murray.cutforth@eu.medical.canon
License: BSD
Download-URL: https://github.com/murraycutforth/pyextrapolation/tarball/0.0.2
Platform: UNKNOWN
Classifier: Development Status :: 3 - Alpha
Classifier: Intended Audience :: Developers
Classifier: Programming Language :: Python :: 3
Requires-Dist: numpy (>=1.11.0)
